pyswit/__init__.py
pyswit/baseAPI.py
pyswit/channel.py
pyswit/idea.py
pyswit/message.py
pyswit/oauth.py
pyswit/project.py
pyswit/task.py
pyswit/user.py
pyswit/webhook.py
pyswit/workspace.py
pyswit-1.0.0.dist-info/LICENSE.md
pyswit-1.0.0.dist-info/METADATA
pyswit-1.0.0.dist-info/WHEEL
pyswit-1.0.0.dist-info/top_level.txt
pyswit-1.0.0.dist-info/RECORD
