Metadata-Version: 2.1
Name: pyswit
Version: 1.0.0
Summary: Swit.io API client
Home-page: https://github.com/sanghunka/pyswit/
Author: Sanghun Kang
Author-email: sanghunka@gmail.com
License: Apache Software License
Keywords: swit swit.io api messenger
Classifier: License :: OSI Approved :: Apache Software License
Classifier: Programming Language :: Python :: 3 :: Only
Classifier: Programming Language :: Python :: 3.6
Classifier: Programming Language :: Python :: 3.7
Classifier: Programming Language :: Python :: 3.8
Classifier: Programming Language :: Python :: 3.9
Classifier: Programming Language :: Python :: 3.10
Classifier: Programming Language :: Python :: 3.11
Classifier: Operating System :: OS Independent
Classifier: Topic :: Communications
Classifier: Topic :: Office/Business
License-File: LICENSE.md
Requires-Dist: requests (>=2.28.1)
